{
    "AX": {
        "error": 0.057612230808853596, 
        "fit": "average_SEM", 
        "value": -0.009048405702560557
    }, 
    "CDD": {
        "error": 0.00020345559688089831, 
        "fit": "average_SEM", 
        "value": 0.0002411621684890027
    }, 
    "H1": {
        "error": 0.11011927139948999, 
        "fit": "average_SEM", 
        "value": 0.03081061931249375
    }, 
    "H2": {
        "error": 0.12081626371396656, 
        "fit": "average_SEM", 
        "value": 0.0036818827162884795
    }, 
    "L1": {
        "error": 0.13267863869371904, 
        "fit": "average_SEM", 
        "value": -0.0355975147074787
    }, 
    "L2": {
        "error": 0.13409757788629306, 
        "fit": "average_SEM", 
        "value": -0.000891343552696829
    }
}