{
    "AX": {
        "error": 0.0556332845208909, 
        "fit": "average_SEM", 
        "value": -0.05476286439176571
    }, 
    "CDD": {
        "error": 0.0002267044320201442, 
        "fit": "average_SEM", 
        "value": 0.00033360342495143415
    }, 
    "H1": {
        "error": 0.11691553696155543, 
        "fit": "average_SEM", 
        "value": 0.7380846684177716
    }, 
    "H2": {
        "error": 0.11351595512392391, 
        "fit": "average_SEM", 
        "value": 0.5586037573715051
    }, 
    "L1": {
        "error": 0.11656209545887063, 
        "fit": "average_SEM", 
        "value": 0.4880789674818516
    }, 
    "L2": {
        "error": 0.21676488812842928, 
        "fit": "average_SEM", 
        "value": 0.7335452124476433
    }
}