{
    "AX": {
        "error": 0.05440252598499678, 
        "fit": "average_SEM", 
        "value": -0.010359187114469629
    }, 
    "CDD": {
        "error": 0.00023462504799612226, 
        "fit": "average_SEM", 
        "value": 0.0002640814890279823
    }, 
    "H1": {
        "error": 0.11916334346232457, 
        "fit": "average_SEM", 
        "value": 0.030284390007727778
    }, 
    "H2": {
        "error": 0.10806075999814906, 
        "fit": "average_SEM", 
        "value": -0.019968046428402886
    }, 
    "L1": {
        "error": 0.11345699059668021, 
        "fit": "average_SEM", 
        "value": -0.0689463779500026
    }, 
    "L2": {
        "error": 0.13119714488370918, 
        "fit": "average_SEM", 
        "value": -0.02026589396603716
    }
}