{
    "Ar36": {
        "error": 0.010974291362980674, 
        "fit": "parabolic", 
        "value": 0.7624473263261029
    }, 
    "Ar37": {
        "error": 0.17259719100661852, 
        "fit": "linear", 
        "value": 61.230484191805488
    }, 
    "Ar38": {
        "error": 0.11188009982095987, 
        "fit": "linear", 
        "value": 1.8172985659588479
    }, 
    "Ar39": {
        "error": 0.12088552068917556, 
        "fit": "parabolic", 
        "value": 117.8108449988797
    }, 
    "Ar40": {
        "error": 0.21832640861991137, 
        "fit": "parabolic", 
        "value": 281.04625867198172
    }, 
    "Ar41": {
        "error": 0.1191814884809413, 
        "fit": "average_SEM", 
        "value": -0.0061517303348591667
    }
}