{
    "AX": {
        "error": 0.05086970900958565, 
        "fit": "average_SEM", 
        "value": -0.020638422058012414
    }, 
    "CDD": {
        "error": 4.1055909820121605e-05, 
        "fit": "average_SEM", 
        "value": -3.310571173642529e-06
    }, 
    "H1": {
        "error": 0.11342873514651489, 
        "fit": "average_SEM", 
        "value": 0.019135036985001838
    }, 
    "H2": {
        "error": 0.1305425437355333, 
        "fit": "average_SEM", 
        "value": -0.007138098313832112
    }, 
    "L1": {
        "error": 0.12491009913433941, 
        "fit": "average_SEM", 
        "value": -0.059942368744911316
    }, 
    "L2": {
        "error": 0.13247629469023295, 
        "fit": "average_SEM", 
        "value": -0.005953826118881503
    }
}