{
    "AX": {
        "error": 0.055533242694571654, 
        "fit": "average_SEM", 
        "value": -0.02540667108357108
    }, 
    "CDD": {
        "error": 0.00010280092394775945, 
        "fit": "average_SEM", 
        "value": 5.6025001686066386e-05
    }, 
    "H1": {
        "error": 0.12991463829395142, 
        "fit": "average_SEM", 
        "value": 0.020318806078284977
    }, 
    "H2": {
        "error": 0.11503382963922626, 
        "fit": "average_SEM", 
        "value": 0.07161434997688047
    }, 
    "L1": {
        "error": 0.11538591176968538, 
        "fit": "average_SEM", 
        "value": 0.03108801445341669
    }, 
    "L2": {
        "error": 0.25095431023695225, 
        "fit": "average_SEM", 
        "value": 0.12318136981921271
    }
}