{
    "AX": {
        "error": 0.05686126255191531, 
        "fit": "average_SEM", 
        "value": -0.030425531516084448
    }, 
    "CDD": {
        "error": 5.6665286100673846e-05, 
        "fit": "average_SEM", 
        "value": 1.7826136900112034e-05
    }, 
    "H1": {
        "error": 0.12345161127645382, 
        "fit": "average_SEM", 
        "value": -0.15936566000261035
    }, 
    "H2": {
        "error": 0.11457549329562523, 
        "fit": "average_SEM", 
        "value": -0.13327891531128747
    }, 
    "L1": {
        "error": 0.11572265837448495, 
        "fit": "average_SEM", 
        "value": -0.17116298833085844
    }, 
    "L2": {
        "error": 0.2133247935539988, 
        "fit": "average_SEM", 
        "value": -0.29019056748754035
    }
}