{
    "AX": {
        "error": 0.05424222523455223, 
        "fit": "average_SEM", 
        "value": 0.02266174228716409
    }, 
    "CDD": {
        "error": 7.968672066418421e-05, 
        "fit": "average_SEM", 
        "value": 4.3292046757414934e-05
    }, 
    "H1": {
        "error": 0.12006251327272666, 
        "fit": "average_SEM", 
        "value": -0.5437141514072815
    }, 
    "H2": {
        "error": 0.10376290512596814, 
        "fit": "average_SEM", 
        "value": -0.405315991739432
    }, 
    "L1": {
        "error": 0.11527573311393235, 
        "fit": "average_SEM", 
        "value": -0.4569120137641827
    }, 
    "L2": {
        "error": 0.25882107268720816, 
        "fit": "average_SEM", 
        "value": -0.5683469352622826
    }
}