{
    "AX": {
        "error": 0.04718538522803562, 
        "fit": "average", 
        "value": -0.08258549430645776
    }, 
    "CDD": {
        "error": 5.3504390012385995e-05, 
        "fit": "average", 
        "value": 2.1646023378707467e-05
    }, 
    "H1": {
        "error": 0.10719684225465653, 
        "fit": "average", 
        "value": -0.021476398112819248
    }, 
    "H2": {
        "error": 0.10922720793273066, 
        "fit": "average", 
        "value": -0.026311612995709572
    }, 
    "L1": {
        "error": 0.09684105817568853, 
        "fit": "average", 
        "value": -0.11134895323285539
    }, 
    "L2": {
        "error": 0.12167483871374211, 
        "fit": "average", 
        "value": -0.0036755189967706153
    }
}