{
    "AX": {
        "error": 0.004066857206774722, 
        "fit": "average_SEM", 
        "value": -0.07198204970053207
    }, 
    "CDD": {
        "error": 6.584137796297251e-06, 
        "fit": "average_SEM", 
        "value": 3.083689928396118e-05
    }, 
    "H1": {
        "error": 0.008215912150026889, 
        "fit": "average_SEM", 
        "value": -0.0013700816527251964
    }, 
    "H2": {
        "error": 0.008947566528140374, 
        "fit": "average_SEM", 
        "value": -0.05270942891593618
    }, 
    "L1": {
        "error": 0.00887925894284568, 
        "fit": "average_SEM", 
        "value": -0.059899504802990375
    }, 
    "L2": {
        "error": 0.009423903322392357, 
        "fit": "average_SEM", 
        "value": -0.021494059721334724
    }
}