{
    "AX": {
        "error": 0.0051058778450459395, 
        "fit": "average_SEM", 
        "value": -0.06491597483671221
    }, 
    "CDD": {
        "error": 2.2561693142146086e-05, 
        "fit": "average_SEM", 
        "value": 0.00042134981155176606
    }, 
    "H1": {
        "error": 0.008080773441975166, 
        "fit": "average_SEM", 
        "value": 0.04095422939636729
    }, 
    "H2": {
        "error": 0.010215411553540653, 
        "fit": "average_SEM", 
        "value": -0.05335104710058026
    }, 
    "L1": {
        "error": 0.009279686779040223, 
        "fit": "average_SEM", 
        "value": -0.07522924508584924
    }, 
    "L2": {
        "error": 0.010685178655472917, 
        "fit": "average_SEM", 
        "value": -0.03834604993544258
    }
}