{
    "AX": {
        "error": 0.05221434860278129, 
        "fit": "average_SEM", 
        "value": -0.05998427014177044
    }, 
    "CDD": {
        "error": 0.00029905833855468054, 
        "fit": "average_SEM", 
        "value": 0.0005938650377781111
    }, 
    "H1": {
        "error": 0.11185343610189719, 
        "fit": "average_SEM", 
        "value": 0.18637931497699659
    }, 
    "H2": {
        "error": 0.11395949139892265, 
        "fit": "average_SEM", 
        "value": 0.01933558615880126
    }, 
    "L1": {
        "error": 0.11787880236337221, 
        "fit": "average_SEM", 
        "value": -0.09021283267065883
    }, 
    "L2": {
        "error": 0.13538044361797527, 
        "fit": "average_SEM", 
        "value": -0.02952342920470983
    }
}