{
    "Ar36": {
        "error": 0.019545604037696264, 
        "fit": "parabolic", 
        "value": 2.4910389910168496
    }, 
    "Ar37": {
        "error": 0.22573261232796948, 
        "fit": "linear", 
        "value": 2.089417282044483
    }, 
    "Ar38": {
        "error": 0.11387052635912964, 
        "fit": "linear", 
        "value": 0.52316878820927004
    }, 
    "Ar39": {
        "error": 0.068000926165170686, 
        "fit": "parabolic", 
        "value": 5.0924008966488383
    }, 
    "Ar40": {
        "error": 0.32502263266500941, 
        "fit": "parabolic", 
        "value": 739.63209672124924
    }, 
    "Ar41": {
        "error": 0.12058990235464319, 
        "fit": "average_SEM", 
        "value": -0.056344268360408026
    }
}