{
    "Ar36": {
        "error": 0.0067731223433741689, 
        "fit": "parabolic", 
        "value": 0.28646997127558621
    }, 
    "Ar37": {
        "error": 0.26366531995541709, 
        "fit": "linear", 
        "value": 10.03455812394772
    }, 
    "Ar38": {
        "error": 0.11468630420375771, 
        "fit": "linear", 
        "value": 0.21903917640440246
    }, 
    "Ar39": {
        "error": 0.062361847655507181, 
        "fit": "parabolic", 
        "value": 1.4651336783362405
    }, 
    "Ar40": {
        "error": 0.15407979602920591, 
        "fit": "parabolic", 
        "value": 84.647445943111322
    }, 
    "Ar41": {
        "error": 0.11221585322723854, 
        "fit": "average_SEM", 
        "value": 0.17472480066353455
    }
}