{
    "AX": {
        "error": 0.050102704156901184, 
        "fit": "average_SEM", 
        "value": -0.006588254536230427
    }, 
    "CDD": {
        "error": 0.00035475135955400017, 
        "fit": "average_SEM", 
        "value": 0.0007874059735816748
    }, 
    "H1": {
        "error": 0.11134497560226633, 
        "fit": "average_SEM", 
        "value": 0.01775027070834767
    }, 
    "H2": {
        "error": 0.12188402046524069, 
        "fit": "average_SEM", 
        "value": -0.018222821946922825
    }, 
    "L1": {
        "error": 0.12852979006614482, 
        "fit": "average_SEM", 
        "value": -0.08445065293932809
    }, 
    "L2": {
        "error": 0.14529763503444754, 
        "fit": "average_SEM", 
        "value": -0.02347519996013337
    }
}