{
    "AX": {
        "error": 0.05576270332903247, 
        "fit": "average_SEM", 
        "value": -0.02119247247101157
    }, 
    "CDD": {
        "error": 0.00021279180177560139, 
        "fit": "average_SEM", 
        "value": 0.00039726819910962754
    }, 
    "H1": {
        "error": 0.12813836397305303, 
        "fit": "average_SEM", 
        "value": -0.13799929557717405
    }, 
    "H2": {
        "error": 0.11118248485789857, 
        "fit": "average_SEM", 
        "value": -0.08708363543426761
    }, 
    "L1": {
        "error": 0.11701922316200737, 
        "fit": "average_SEM", 
        "value": -0.13166939091461244
    }, 
    "L2": {
        "error": 0.2659399914487408, 
        "fit": "average_SEM", 
        "value": -0.18630813571702068
    }
}