{
    "AX": {
        "error": 0.04629176065113448, 
        "fit": "average_SEM", 
        "value": -0.0392738058972706
    }, 
    "CDD": {
        "error": 0.00021241883820363538, 
        "fit": "average_SEM", 
        "value": 0.00029158467029143743
    }, 
    "H1": {
        "error": 0.11004152053551133, 
        "fit": "average_SEM", 
        "value": 0.2962512361157375
    }, 
    "H2": {
        "error": 0.10708061994117879, 
        "fit": "average_SEM", 
        "value": 0.19852499954868108
    }, 
    "L1": {
        "error": 0.11545879240471828, 
        "fit": "average_SEM", 
        "value": 0.15884952916530892
    }, 
    "L2": {
        "error": 0.22976504969842, 
        "fit": "average_SEM", 
        "value": 0.4087631144444458
    }
}