{
    "AX": {
        "error": 0.04642018113616166, 
        "fit": "average_SEM", 
        "value": -0.03181022709529651
    }, 
    "CDD": {
        "error": 0.0, 
        "fit": "average_SEM", 
        "value": 2.1075235743974818e-05
    }, 
    "H1": {
        "error": 0.11020480045015905, 
        "fit": "average_SEM", 
        "value": 0.10756713327608505
    }, 
    "H2": {
        "error": 0.10839618477824307, 
        "fit": "average_SEM", 
        "value": 0.11149343501698847
    }, 
    "L1": {
        "error": 0.11848684469815152, 
        "fit": "average_SEM", 
        "value": 0.08561275789703605
    }, 
    "L2": {
        "error": 0.210443284765596, 
        "fit": "average_SEM", 
        "value": 0.336539966519922
    }
}