{
    "AX": {
        "error": 0.05758313308568563, 
        "fit": "average_SEM", 
        "value": -0.03025096714748846
    }, 
    "CDD": {
        "error": 0.00029179491438558776, 
        "fit": "average_SEM", 
        "value": 0.0006481074378825724
    }, 
    "H1": {
        "error": 0.10499520397582417, 
        "fit": "average_SEM", 
        "value": 0.20264734029769899
    }, 
    "H2": {
        "error": 0.10384713730965672, 
        "fit": "average_SEM", 
        "value": 0.1491216161986813
    }, 
    "L1": {
        "error": 0.11890926533301854, 
        "fit": "average_SEM", 
        "value": 0.09194574905147117
    }, 
    "L2": {
        "error": 0.22818391764965873, 
        "fit": "average_SEM", 
        "value": 0.45918280247715304
    }
}