{
    "Ar36": {
        "error": 0.0018360236986008794, 
        "fit": "parabolic", 
        "value": 0.015921200659475776
    }, 
    "Ar37": {
        "error": 0.12820528465433725, 
        "fit": "linear", 
        "value": -0.024385810164827916
    }, 
    "Ar38": {
        "error": 0.1121817411501793, 
        "fit": "linear", 
        "value": -0.09110463108115549
    }, 
    "Ar39": {
        "error": 0.06125523196519532, 
        "fit": "parabolic", 
        "value": -0.020260644740716784
    }, 
    "Ar40": {
        "error": 0.11732368304549397, 
        "fit": "parabolic", 
        "value": 4.4817477698094255
    }, 
    "Ar41": {
        "error": 0.12340049265071427, 
        "fit": "average_SEM", 
        "value": -0.051388335389310667
    }
}