{
    "Ar36": {
        "error": 0.0013992781653754515, 
        "fit": "parabolic", 
        "value": 0.0069734624660452655
    }, 
    "Ar37": {
        "error": 0.14074592071793252, 
        "fit": "linear", 
        "value": -0.056051020027641306
    }, 
    "Ar38": {
        "error": 0.11648335112869136, 
        "fit": "linear", 
        "value": -0.088278781871050468
    }, 
    "Ar39": {
        "error": 0.056371821742353306, 
        "fit": "parabolic", 
        "value": -0.041684314142108575
    }, 
    "Ar40": {
        "error": 0.11895007069154132, 
        "fit": "parabolic", 
        "value": 1.7910270457147388
    }, 
    "Ar41": {
        "error": 0.11679586109012842, 
        "fit": "average_SEM", 
        "value": -0.052736057985530355
    }
}