{
    "Ar36": {
        "error": 0.029228837999121435, 
        "fit": "linear", 
        "value": 5.7794951540730901
    }, 
    "Ar37": {
        "error": 0.15423476792833576, 
        "fit": "linear", 
        "value": 10.809291950357757
    }, 
    "Ar38": {
        "error": 0.12808869766187791, 
        "fit": "linear", 
        "value": 1.7993453573141887
    }, 
    "Ar39": {
        "error": 0.08439503652236921, 
        "fit": "linear", 
        "value": 30.868504381698759
    }, 
    "Ar40": {
        "error": 0.51400657290126206, 
        "fit": "linear", 
        "value": 1738.2795389059725
    }, 
    "Ar41": {
        "error": 0.12613027851848949, 
        "fit": "average_SEM", 
        "value": -0.010665372895115675
    }
}