{
    "Ar36": {
        "error": 0.040065824266197307, 
        "fit": "parabolic", 
        "value": 8.8526011951499086
    }, 
    "Ar37": {
        "error": 0.12943553644835173, 
        "fit": "linear", 
        "value": 3.5060948632079034
    }, 
    "Ar38": {
        "error": 0.11644828646624072, 
        "fit": "linear", 
        "value": 2.5927088854912874
    }, 
    "Ar39": {
        "error": 0.081962064533761772, 
        "fit": "parabolic", 
        "value": 35.597191496661836
    }, 
    "Ar40": {
        "error": 0.6349723130761814, 
        "fit": "parabolic", 
        "value": 2641.1564973110421
    }, 
    "Ar41": {
        "error": 0.12198248965270574, 
        "fit": "average_SEM", 
        "value": 0.024502526072901674
    }
}