{
    "Ar36": {
        "error": 0.0023080542605352634, 
        "fit": "linear", 
        "value": 0.033178526870782842
    }, 
    "Ar37": {
        "error": 0.13007885078057851, 
        "fit": "linear", 
        "value": 0.41230098424617745
    }, 
    "Ar38": {
        "error": 0.31041809814481996, 
        "fit": "linear", 
        "value": 0.080962311177809221
    }, 
    "Ar39": {
        "error": 0.058083517590290616, 
        "fit": "linear", 
        "value": 2.6674933995852834
    }, 
    "Ar40": {
        "error": 0.1336862077144173, 
        "fit": "linear", 
        "value": 11.413347499982077
    }, 
    "Ar41": {
        "error": 0.12152973228645221, 
        "fit": "average_SEM", 
        "value": -0.067373520038927381
    }
}