{
    "Ar36": {
        "error": 0.015255863681980205, 
        "fit": "Parabolic", 
        "value": 2.0133096892897098
    }, 
    "Ar37": {
        "error": 0.12689466823067874, 
        "fit": "linear", 
        "value": 12.403861899121729
    }, 
    "Ar38": {
        "error": 0.10507236556074272, 
        "fit": "linear", 
        "value": 0.60137407742961635
    }, 
    "Ar39": {
        "error": 0.059343464089628817, 
        "fit": "Parabolic", 
        "value": 10.674887609472263
    }, 
    "Ar40": {
        "error": 0.24969031565652547, 
        "fit": "Parabolic", 
        "value": 616.42023516158076
    }, 
    "Ar41": {
        "error": 0.10395148881368713, 
        "fit": "linear", 
        "value": 0.034597672634192347
    }
}