{
    "Ar36": {
        "error": 0.015121247925550788, 
        "fit": "Parabolic", 
        "value": 2.2706750608510635
    }, 
    "Ar37": {
        "error": 0.16817447088403381, 
        "fit": "linear", 
        "value": 127.82686691105901
    }, 
    "Ar38": {
        "error": 0.097299590918868431, 
        "fit": "linear", 
        "value": 0.87263601559449078
    }, 
    "Ar39": {
        "error": 0.062564890202318243, 
        "fit": "Parabolic", 
        "value": 15.836802988645749
    }, 
    "Ar40": {
        "error": 0.29907741845139946, 
        "fit": "Parabolic", 
        "value": 690.43823662669467
    }, 
    "Ar41": {
        "error": 0.10746206268511904, 
        "fit": "linear", 
        "value": 0.0041283908094775414
    }
}